{
  "https://www.bilibili.com/video/BV1Gz421y7en/?spm_id_from=333.337.search-card.all.click": {
    "data": {
      "title": "精英比我们更努力吗？——五十分钟读懂《精英的傲慢》_哔哩哔哩_bilibili",
      "description": "",
      "image": "https://images.weserv.nl/?url=//i2.hdslb.com/bfs/archive/45d26ebc42d6e0a7b5b76c255c21750c57f68d63.jpg@500w_500h_1c.png",
      "siteName": "www.bilibili.com",
      "url": "https://www.bilibili.com/video/BV1Gz421y7en/?spm_id_from=333.337.search-card.all.click"
    },
    "timestamp": 1767168240696
  },
  "https://neodb.social/~neodb~/movie/2jGT1CtdgHPjirJj3bb0PA": {
    "data": {
      "title": "坚如磐石",
      "description": "金江市副市长郑刚（张国立 饰）之子苏见明（雷佳音 饰）不顾父亲的劝阻，应邀赴约首富黎志田（于和伟 饰）的“鸿门宴”，不料却被迫观看了一出“人手下火锅”的猖狂戏码。旧案翻起，风雨欲来，各方蛰伏势力蠢蠢欲动，筹谋与算计、审视与怀疑，光怪陆离之中，人性欲望翻腾，谁将撕去最后的面具？",
      "image": "https://images.weserv.nl/?url=https://neodb.social/m/item/doubanmovie/2023/10/03/db405751-1d78-4d27-83f9-c4cffd81229d.jpg",
      "siteName": "NeoDB 电影",
      "url": "https://neodb.social/~neodb~/movie/2jGT1CtdgHPjirJj3bb0PA"
    },
    "timestamp": 1767168241194
  },
  "https://neodb.social/~neodb~/tv/season/3nSJNWjFRGgV7QoR7qS6MA": {
    "data": {
      "title": "老舅",
      "description": "《老舅》是由韩三平监制&编剧、孔二狗导演&编剧，郭京飞、王佳佳领衔主演，陈明昊、张歆艺特邀主演，刘奕铁、刘佩琦特别出演。\n\n讲述了高校毕业生老舅（崔国明），从国营大厂开始到下岗后，凭借自己的聪明才智开启了一系列靠谱或者不靠谱的折腾史。通过老舅和其家人、身边人在90年代巨变中的喜泪交加的奋斗故事，展示了大时代变",
      "image": "https://images.weserv.nl/?url=https://neodb.social/m/item/tmdb_tvseason/2025/12/16/d75bf328-4fe8-4282-95d2-b45329d67437.jpg",
      "siteName": "NeoDB 剧集",
      "url": "https://neodb.social/~neodb~/tv/season/3nSJNWjFRGgV7QoR7qS6MA"
    },
    "timestamp": 1767168241629
  },
  "https://mas.to/@alternativeto/115763128814869394": {
    "data": {
      "title": "AlternativeTo (@alternativeto@mas.to)",
      "description": "Attached: 1 image\n\nMicrosoft recently updated Notepad for Windows 11 Insiders with table formatting tools, more responsive AI writing features and streaming responses.\nhttps://alternativeto.net/news/2025/12/microsoft-recently-updated-notepad-with-table-support-and-more-responsive-ai-features/",
      "image": "https://media.mas.to/media_attachments/files/115/763/128/690/229/071/original/04a9cafb0f92d9db.png",
      "siteName": "mas.to",
      "url": "https://mas.to/@alternativeto/115763128814869394"
    },
    "timestamp": 1767170930637
  },
  "https://gist.github.com/hackermondev/5e2cdc32849405fff6b46957747a2d28": {
    "data": {
      "title": "How we pwned X (Twitter), Vercel, Cursor, Discord, and hundreds of companies through a supply-chain attack",
      "description": "How we pwned X (Twitter), Vercel, Cursor, Discord, and hundreds of companies through a supply-chain attack - writeup.md",
      "image": "https://github.githubassets.com/assets/gist-og-image-54fd7dc0713e.png",
      "siteName": "Gist",
      "url": "https://gist.github.com/hackermondev/5e2cdc32849405fff6b46957747a2d28"
    },
    "timestamp": 1767170930812
  },
  "https://neodb.social/~neodb~/movie/5oimwyduqzMgtkPM38MQP2": {
    "data": {
      "title": "巨洪",
      "description": "科幻灾难大片《巨洪》讲述了在地球被大洪水淹没前的最后一天，对人类抱有最后一丝希望的人们在淹水的公寓楼里挣扎求生的故事。",
      "image": "https://images.weserv.nl/?url=https://neodb.social/m/item/doubanmovie/2025/12/21/798c5a38-08ca-4ce3-8d5e-45e7b354c4c6.jpg",
      "siteName": "NeoDB 电影",
      "url": "https://neodb.social/~neodb~/movie/5oimwyduqzMgtkPM38MQP2"
    },
    "timestamp": 1767170932359
  },
  "https://neodb.social/~neodb~/movie/1iFeoGvCEp37fIK1XzpTmq": {
    "data": {
      "title": "无可奈何",
      "description": "中产阶级男子刘万洙失业后为了再就业，在一本杂志上刊登了一个虚假的招聘广告，决定淘汰五个比他更有才华、更年轻、更英俊的人。他在无奈与希望之间来回穿梭，将竞争对手一一杀死……",
      "image": "https://images.weserv.nl/?url=https://neodb.social/m/item/imdb/2025/12/30/4edae111-ad17-40bb-8b24-ca2315037782.jpg",
      "siteName": "NeoDB 电影",
      "url": "https://neodb.social/~neodb~/movie/1iFeoGvCEp37fIK1XzpTmq"
    },
    "timestamp": 1767170932398
  },
  "https://neodb.social/~neodb~/book/0wXYrWxPKDJ2r15RWR7Wgh": {
    "data": {
      "title": "告白",
      "description": "日本銷售破67萬冊\n獲獎記錄\n★2009年本屋大賞第1名\n★第29回小說推理新人獎\n★週刊文春「2008年Mystery Best 10」第1名\n★寶島社「2009年這本推理小說真厲害！」第4名\n當倫理和正義分歧，你該選哪邊？\n殺人者的與復仇者的心理演進，輪番敲擊著我們內心的道德尺度\n一位中學女老師在校園游泳",
      "image": "https://images.weserv.nl/?url=https://neodb.social/m/book/2021/09/15ae428352-31b1-4bc0-9d73-2161802fae97.jpg",
      "siteName": "NeoDB 图书",
      "url": "https://neodb.social/~neodb~/book/0wXYrWxPKDJ2r15RWR7Wgh"
    },
    "timestamp": 1767170932443
  },
  "https://neodb.social/~neodb~/book/7S1fS6FPhnYWDv5Nve0Z6i": {
    "data": {
      "title": "通往冈仁波齐的路",
      "description": "《通往冈仁波齐的路》是著名导演张杨的首部文字作品。张杨在书中回顾了自己二十年的从影历程，以及备受瞩目的电影《冈仁波齐》和《皮绳上的魂》的创作故事。传奇的经历与颇具张力的行文风格无不透露着张杨独特的艺术观与坦诚的人生观。\n作为内地第六代导演的代表人物，张杨持续不断地进行着风格实验与自我突破，凭借《洗澡》《向日葵",
      "image": "https://images.weserv.nl/?url=https://neodb.social/m/book/2021/11/288866f72a-462d-4bbd-b8f9-4047909c9adb.jpg",
      "siteName": "NeoDB 图书",
      "url": "https://neodb.social/~neodb~/book/7S1fS6FPhnYWDv5Nve0Z6i"
    },
    "timestamp": 1767170932470
  },
  "https://neodb.social/~neodb~/tv/season/7QM90qIaCSIQnWLWL4Rvn2": {
    "data": {
      "title": "反人类暴行",
      "description": "1992年，哈尔滨731陈列馆工作人员小金在整理史料时，发现这段历史的记录残缺不全，为寻找真相，他踏上了一场跨越数十年的跨国取证之旅，逐渐还原出那段被尘封的黑暗岁月真相。故事采取双时间线叙事，镜头回到日军侵华期间的哈尔滨，通过几个当事人的视角，深刻揭露日军731部队残酷的人体实验和泯灭人性的暴行，鞭笞日本军国",
      "image": "https://images.weserv.nl/?url=https://neodb.social/m/item/doubanmovie/2025/12/29/745c6813-789f-4037-ad29-50f4a96bde54.jpg",
      "siteName": "NeoDB 剧集",
      "url": "https://neodb.social/~neodb~/tv/season/7QM90qIaCSIQnWLWL4Rvn2"
    },
    "timestamp": 1767170932976
  }
}